x_twitter_posting_mcp/__init__.py
x_twitter_posting_mcp/server.py
x_twitter_posting_mcp-0.1.0.dist-info/licenses/LICENSE
x_twitter_posting_mcp-0.1.0.dist-info/METADATA
x_twitter_posting_mcp-0.1.0.dist-info/WHEEL
x_twitter_posting_mcp-0.1.0.dist-info/entry_points.txt
x_twitter_posting_mcp-0.1.0.dist-info/top_level.txt
x_twitter_posting_mcp-0.1.0.dist-info/RECORD
