Metadata-Version: 2.4
Name: x-twitter-posting-mcp
Version: 0.1.0
Summary: An MCP server for posting tweets and threads to X (Twitter).
Author-email: DevRico003 <devrico003@example.com>
Project-URL: Homepage, https://github.com/DevRico003/x-twitter-posting-mcp
Project-URL: Bug Tracker, https://github.com/DevRico003/x-twitter-posting-mcp/issues
Classifier: Programming Language :: Python :: 3
Classifier: License :: OSI Approved :: MIT License
Classifier: Operating System :: OS Independent
Classifier: Topic :: Communications :: Chat
Classifier: Topic :: Internet
Classifier: Development Status :: 3 - Alpha
Requires-Python: >=3.10
License-File: LICENSE
Requires-Dist: mcp>=1.5.0
Requires-Dist: tweepy>=4.14.0
Requires-Dist: python-dotenv>=1.0.0
Requires-Dist: httpx>=0.27.0
Dynamic: license-file
